starfish_engine-0.0.2.dist-info/METADATA
starfish_engine-0.0.2.dist-info/WHEEL
starfish/__init__.py
starfish/engine.pyi
starfish/engine.cpython-38-x86_64-linux-gnu.so
starfish_engine-0.0.2.dist-info/RECORD
