Metadata-Version: 2.1
Name: starfish-engine
Version: 0.0.2
Classifier: Programming Language :: Rust
Classifier: Programming Language :: Python :: Implementation :: CPython
Classifier: Programming Language :: Python :: Implementation :: PyPy
Requires-Dist: pandas ==2.2.1
Requires-Dist: TA-Lib ==0.4.28
Requires-Python: >=3.8
